emailtools
