Metadata-Version: 1.0
Name: django-emailtools
Version: 0.2.1
Summary: 
